YHandler/AuthManager.py
YHandler/Extensions.py
YHandler/OAuth1Lite.py
YHandler/YHandler.py
YHandler/YQuery.py
YHandler/__init__.py
YHandler/Selectors/BaseSelector.py
YHandler/Selectors/DefaultSelector.py
YHandler/Selectors/LxmlSelector.py
YHandler/Selectors/__init__.py
YHandler-1.0.2.dist-info/DESCRIPTION.rst
YHandler-1.0.2.dist-info/METADATA
YHandler-1.0.2.dist-info/RECORD
YHandler-1.0.2.dist-info/WHEEL
YHandler-1.0.2.dist-info/metadata.json
YHandler-1.0.2.dist-info/top_level.txt
